{
  "Subject": {
    "Id": "i9383584",
    "Name": "William Alexander Mackay",
    "Gender": "Male",
    "DateOfBirth": "24/Feb/1900",
    "DateOfDeath": "24/Sep/1982"
  },
  "Parents": [
    {
      "Id": "i32797554",
      "Name": "Isabella Mackay",
      "Gender": "Female",
      "DateOfBirth": "7/Aug/1860",
      "DateOfDeath": "after 1923",
      "RelationToSubject": "mother"
    },
    {
      "Id": "i60572122",
      "Name": "James Mackay",
      "Gender": "Male",
      "DateOfBirth": "12/Apr/1861",
      "DateOfDeath": "before 1911",
      "RelationToSubject": "father"
    }
  ],
  "Siblings": [
    {
      "Id": "i16587624",
      "Name": "Lucy Mackay",
      "Gender": "Female",
      "DateOfBirth": "23/Sep/1889",
      "DateOfDeath": "15/May/1970",
      "RelationToSubject": "sister",
      "ParentGroupIds": [
        [
          "i32797554",
          "i60572122"
        ]
      ]
    },
    {
      "Id": "i72941728",
      "Name": "George Mackay",
      "Gender": "Male",
      "DateOfBirth": "12/Nov/1890",
      "DateOfDeath": "",
      "RelationToSubject": "brother",
      "ParentGroupIds": [
        [
          "i32797554",
          "i60572122"
        ]
      ]
    },
    {
      "Id": "i22499038",
      "Name": "Janet Mackay",
      "Gender": "Female",
      "DateOfBirth": "12/Nov/1890",
      "DateOfDeath": "15/May/1891",
      "RelationToSubject": "sister",
      "ParentGroupIds": [
        [
          "i32797554",
          "i60572122"
        ]
      ]
    },
    {
      "Id": "i51252926",
      "Name": "Annie Mackay",
      "Gender": "Female",
      "DateOfBirth": "15/Dec/1892",
      "DateOfDeath": "1918",
      "RelationToSubject": "sister",
      "ParentGroupIds": [
        [
          "i32797554",
          "i60572122"
        ]
      ]
    },
    {
      "Id": "i48909111",
      "Name": "Kenneth Mackay",
      "Gender": "Male",
      "DateOfBirth": "2/Feb/1895",
      "DateOfDeath": "",
      "RelationToSubject": "brother",
      "ParentGroupIds": [
        [
          "i32797554",
          "i60572122"
        ]
      ]
    },
    {
      "Id": "i57646474",
      "Name": "John Paul Mackay",
      "Gender": "Male",
      "DateOfBirth": "13/Mar/1899",
      "DateOfDeath": "3/Jul/1969",
      "RelationToSubject": "brother",
      "ParentGroupIds": [
        [
          "i32797554",
          "i60572122"
        ]
      ]
    },
    {
      "Id": "i9383584",
      "Name": "William Alexander Mackay",
      "Gender": "Male",
      "DateOfBirth": "24/Feb/1900",
      "DateOfDeath": "24/Sep/1982",
      "RelationToSubject": "self",
      "ParentGroupIds": [
        [
          "i32797554",
          "i60572122"
        ]
      ]
    },
    {
      "Id": "i178005",
      "Name": "Margaret Moyes Mackay",
      "Gender": "Female",
      "DateOfBirth": "27/Jun/1901",
      "DateOfDeath": "1973",
      "RelationToSubject": "sister",
      "ParentGroupIds": [
        [
          "i32797554",
          "i60572122"
        ]
      ]
    }
  ],
  "Spouses": [
    {
      "Id": "i48241984",
      "Name": "Mary Ann Cumming",
      "Gender": "Female",
      "DateOfBirth": "26/Jul/1900",
      "DateOfDeath": "8/Oct/1981",
      "RelationToSubject": "wife",
      "DateOfMarriage": "21/Mar/1930",
      "DateOfDivorce": ""
    }
  ],
  "Children": [
    {
      "Id": "i43065376",
      "Name": "Donald James Mackay",
      "Gender": "Male",
      "DateOfBirth": "1931",
      "DateOfDeath": "29/Dec/2011",
      "RelationToSubject": "son",
      "ParentIds": [
        "i9383584",
        "i48241984"
      ]
    },
    {
      "Id": "i61915200",
      "Name": "X",
      "Gender": "Male",
      "DateOfBirth": "27/May/1932",
      "DateOfDeath": "",
      "RelationToSubject": "son",
      "ParentIds": [
        "i9383584",
        "i48241984"
      ]
    },
    {
      "Id": "i75066880",
      "Name": "Alexina Mackay",
      "Gender": "Female",
      "DateOfBirth": "11/Jan/1935",
      "DateOfDeath": "1935",
      "RelationToSubject": "daughter",
      "ParentIds": [
        "i9383584",
        "i48241984"
      ]
    },
    {
      "Id": "i25303611",
      "Name": "Isabella Mackay",
      "Gender": "Female",
      "DateOfBirth": "1/Jan/1936",
      "DateOfDeath": "18/Dec/2019",
      "RelationToSubject": "daughter",
      "ParentIds": [
        "i9383584",
        "i48241984"
      ]
    },
    {
      "Id": "i41265374",
      "Name": "Anna Jess Mackay",
      "Gender": "Female",
      "DateOfBirth": "7/Jul/1938",
      "DateOfDeath": "12/Mar/2021",
      "RelationToSubject": "daughter",
      "ParentIds": [
        "i9383584",
        "i48241984"
      ]
    },
    {
      "Id": "i81915607",
      "Name": "X",
      "Gender": "Male",
      "DateOfBirth": "1939",
      "DateOfDeath": "",
      "RelationToSubject": "son",
      "ParentIds": [
        "i9383584",
        "i48241984"
      ]
    },
    {
      "Id": "i60810514",
      "Name": "X",
      "Gender": "Male",
      "DateOfBirth": "2/Jan/1942",
      "DateOfDeath": "",
      "RelationToSubject": "son",
      "ParentIds": [
        "i9383584",
        "i48241984"
      ]
    }
  ]
}