{
  "Id": "i97706646",
  "Name": "Hannah Elder Falloon",
  "Gender": "Female",
  "Relationship": "Self",
  "DateOfBirth": "7/Dec/1921",
  "DateOfDeath": "1982",
  "Parents": [
    {
      "Id": "i11230712",
      "Name": "Campbell Elizabeth Munn",
      "Gender": "Female",
      "Relationship": "mother",
      "DateOfBirth": "",
      "DateOfDeath": "",
      "Parents": []
    },
    {
      "Id": "i14463787",
      "Name": "William John Falloon",
      "Gender": "Male",
      "Relationship": "father",
      "DateOfBirth": "",
      "DateOfDeath": "",
      "Parents": []
    }
  ]
}