{
  "Subject": {
    "Id": "i52613824",
    "Name": "Ann Ross",
    "Gender": "Female",
    "DateOfBirth": "28/Nov/1890",
    "DateOfDeath": "27/Jun/1980"
  },
  "Parents": [
    {
      "Id": "i75057664",
      "Name": "John Ross",
      "Gender": "Male",
      "DateOfBirth": "1861",
      "DateOfDeath": "",
      "RelationToSubject": "father"
    },
    {
      "Id": "i59851647",
      "Name": "Marion Cumming",
      "Gender": "Female",
      "DateOfBirth": "20/May/1863",
      "DateOfDeath": "15/Nov/1954",
      "RelationToSubject": "mother"
    }
  ],
  "Siblings": [
    {
      "Id": "i52613824",
      "Name": "Ann Ross",
      "Gender": "Female",
      "DateOfBirth": "28/Nov/1890",
      "DateOfDeath": "27/Jun/1980",
      "RelationToSubject": "self",
      "ParentGroupIds": [
        [
          "i59851647",
          "i75057664"
        ]
      ]
    },
    {
      "Id": "i22731476",
      "Name": "Hugh Alexander Ross",
      "Gender": "Male",
      "DateOfBirth": "17/Nov/1896",
      "DateOfDeath": "",
      "RelationToSubject": "brother",
      "ParentGroupIds": [
        [
          "i59851647",
          "i75057664"
        ]
      ]
    }
  ],
  "Spouses": [
    {
      "Id": "i65815518",
      "Name": "Thomas Mitchell",
      "Gender": "Male",
      "DateOfBirth": "2/Feb/1891",
      "DateOfDeath": "4/May/1972",
      "RelationToSubject": "husband",
      "DateOfMarriage": "15/Aug/1925",
      "DateOfDivorce": ""
    }
  ],
  "Children": [
    {
      "Id": "i49269448",
      "Name": "Donald Charles Mitchell",
      "Gender": "Male",
      "DateOfBirth": "26/Mar/1929",
      "DateOfDeath": "12/Mar/1982",
      "RelationToSubject": "son",
      "ParentIds": [
        "i65815518",
        "i52613824"
      ]
    }
  ]
}