{
  "Id": "i92463484",
  "Name": "William Hawthorn",
  "Gender": "Male",
  "Relationship": "Self",
  "DateOfBirth": "about 1847",
  "DateOfDeath": "before 1921",
  "Children": [
    {
      "Id": "i16695817",
      "Name": "Joseph Hawthorn",
      "Gender": "Male",
      "Relationship": "son",
      "DateOfBirth": "about 1873",
      "DateOfDeath": "",
      "Children": []
    },
    {
      "Id": "i91501446",
      "Name": "Robert Hawthorn",
      "Gender": "Male",
      "Relationship": "son",
      "DateOfBirth": "about 1875",
      "DateOfDeath": "",
      "Children": []
    },
    {
      "Id": "i21482384",
      "Name": "James Hawthorn",
      "Gender": "Male",
      "Relationship": "son",
      "DateOfBirth": "about 1877",
      "DateOfDeath": "",
      "Children": []
    },
    {
      "Id": "i88518114",
      "Name": "Edward Hawthorn",
      "Gender": "Male",
      "Relationship": "son",
      "DateOfBirth": "about 1886",
      "DateOfDeath": "",
      "Children": []
    },
    {
      "Id": "i30039040",
      "Name": "Thomas Hawthorn",
      "Gender": "Male",
      "Relationship": "son",
      "DateOfBirth": "28/Jun/1888",
      "DateOfDeath": "before 1946",
      "Children": [
        {
          "Id": "i51411241",
          "Name": "Edward Joseph Hawthorne",
          "Gender": "Male",
          "Relationship": "son",
          "DateOfBirth": "about 13/Apr/1923",
          "DateOfDeath": "2013",
          "Children": [
            {
              "Id": "i26071271",
              "Name": "X",
              "Gender": "Male",
              "Relationship": "son",
              "DateOfBirth": "27/Jul/1948",
              "DateOfDeath": "",
              "Children": [
                {
                  "Id": "i23872865",
                  "Name": "X",
                  "Gender": "Female",
                  "Relationship": "daughter",
                  "DateOfBirth": "1986",
                  "DateOfDeath": "",
                  "Children": [
                    {
                      "Id": "i25146614",
                      "Name": "X",
                      "Gender": "Male",
                      "Relationship": "son",
                      "DateOfBirth": "3/Aug/2021",
                      "DateOfDeath": "",
                      "Children": []
                    }
                  ]
                }
              ]
            }
          ]
        }
      ]
    }
  ]
}